blogus/__init__.py
blogus/cli.py
blogus/core.py
blogus/web.py
blogus/web_cli.py
blogus-0.1.0.dist-info/LICENSE
blogus-0.1.0.dist-info/METADATA
blogus-0.1.0.dist-info/WHEEL
blogus-0.1.0.dist-info/entry_points.txt
blogus-0.1.0.dist-info/RECORD
