Metadata-Version: 2.3
Name: blogus
Version: 0.1.0
Summary: A library for crafting, analyzing, and perfecting AI prompts
Author: Dipankar Sarkar
Author-email: me@dipankar.name
Requires-Python: >=3.11,<4.0
Classifier: Programming Language :: Python :: 3
Classifier: Programming Language :: Python :: 3.11
Classifier: Programming Language :: Python :: 3.12
Classifier: Programming Language :: Python :: 3.13
Provides-Extra: web
Requires-Dist: anthropic (>=0.34.2,<0.35.0)
Requires-Dist: click (>=8.1.7,<9.0.0)
Requires-Dist: fastapi (>=0.115.0,<0.116.0) ; extra == "web"
Requires-Dist: groq (>=0.11.0,<0.12.0)
Requires-Dist: jinja2 (>=3.1.5,<4.0.0) ; extra == "web"
Requires-Dist: litellm (>=1.40.0,<2.0.0)
Requires-Dist: openai (>=1.0.0,<2.0.0)
Requires-Dist: pydantic (>=2.9.2,<3.0.0) ; extra == "web"
Requires-Dist: python-dotenv (>=1.0.1,<2.0.0)
Requires-Dist: uvicorn (>=0.30.6,<0.31.0) ; extra == "web"
